aio_yte/__init__.py
aio_yte/context.py
aio_yte/document.py
aio_yte/exceptions.py
aio_yte/process.py
aio_yte-2.0.5.dist-info/LICENSE
aio_yte-2.0.5.dist-info/METADATA
aio_yte-2.0.5.dist-info/WHEEL
aio_yte-2.0.5.dist-info/entry_points.txt
aio_yte-2.0.5.dist-info/RECORD
