Metadata-Version: 2.1
Name: aio-yte
Version: 2.0.5
Summary: An Async YAML template engine with Python expressions
Home-page: https://github.com/Akm0d/aio-yte
License: MIT
Author: Johannes Köster
Author-email: johannes.koester@tu-dortmund.de
Requires-Python: >=3.7
Classifier: License :: OSI Approved :: MIT License
Classifier: Programming Language :: Python :: 3
Classifier: Programming Language :: Python :: 3.7
Classifier: Programming Language :: Python :: 3.8
Classifier: Programming Language :: Python :: 3.9
Classifier: Programming Language :: Python :: 3.10
Classifier: Programming Language :: Python :: 3.11
Classifier: Programming Language :: Python :: 3.12
Requires-Dist: aioconsole (>=0.8.0)
Requires-Dist: dpath (>=2.1,<3.0)
Requires-Dist: plac (>=1.3.4,<2.0.0)
Requires-Dist: pyyaml (>=6.0,<7.0)
Project-URL: Repository, https://github.com/yte-template-engine/yte
